odoo/addons/currency_rate_update_RO_BNR/README.rst
odoo/addons/currency_rate_update_RO_BNR/__init__.py
odoo/addons/currency_rate_update_RO_BNR/__manifest__.py
odoo/addons/currency_rate_update_RO_BNR/i18n/currency_rate_update_RO_BNR.pot
odoo/addons/currency_rate_update_RO_BNR/models/__init__.py
odoo/addons/currency_rate_update_RO_BNR/models/res_currency_rate_provider_RO_BNR.py
odoo/addons/currency_rate_update_RO_BNR/readme/CONTRIBUTORS.md
odoo/addons/currency_rate_update_RO_BNR/readme/DESCRIPTION.md
odoo/addons/currency_rate_update_RO_BNR/readme/INSTALL.md
odoo/addons/currency_rate_update_RO_BNR/static/description/icon.png
odoo/addons/currency_rate_update_RO_BNR/static/description/index.html
odoo/addons/currency_rate_update_RO_BNR/tests/__init__.py
odoo/addons/currency_rate_update_RO_BNR/tests/nbrfxrates.xml
odoo/addons/currency_rate_update_RO_BNR/tests/nbrfxrates2022.xml
odoo/addons/currency_rate_update_RO_BNR/tests/nbrfxrates2023.xml
odoo/addons/currency_rate_update_RO_BNR/tests/nbrfxrates2024.xml
odoo/addons/currency_rate_update_RO_BNR/tests/nbrfxrates2025.xml
odoo/addons/currency_rate_update_RO_BNR/tests/test_currency_rate_update_ro_bnr.py
odoo_addon_currency_rate_update_ro_bnr-17.0.1.6.0.dist-info/METADATA
odoo_addon_currency_rate_update_ro_bnr-17.0.1.6.0.dist-info/WHEEL
odoo_addon_currency_rate_update_ro_bnr-17.0.1.6.0.dist-info/top_level.txt
odoo_addon_currency_rate_update_ro_bnr-17.0.1.6.0.dist-info/RECORD
