Metadata-Version: 2.1
Name: odoo-addon-currency_rate_update_RO_BNR
Version: 17.0.1.6.0
Requires-Python: >=3.10
Requires-Dist: odoo-addon-currency_rate_update>=17.0dev,<17.1dev
Requires-Dist: odoo>=17.0a,<17.1dev
Summary: Currency Rate Update National Bank of Romania service
Home-page: https://github.com/OCA/l10n-romania
License: AGPL-3
Author: SM Freelancer,NextERP Romania,Forest and Biomass Romania,Odoo Community Association (OCA)
Author-email: support@odoo-community.org
Classifier: Programming Language :: Python
Classifier: Framework :: Odoo
Classifier: Framework :: Odoo :: 17.0
Classifier: License :: OSI Approved :: GNU Affero General Public License v3
Classifier: Development Status :: 4 - Beta
